<?xml version="1.0"?>
<ruleset xmlns:xsi="http://www.w3.org/2001/XMLSchema-instance"
         name="Starisian Plugin Standard"
         xsi:noNamespaceSchemaLocation="https://raw.githubusercontent.com/PHPCSStandards/PHP_CodeSniffer/master/phpcs.xsd">

  <description>
    Starisian Technologies strict coding standard.
    Combines WordPress VIP, PHPCompatibility, Modern PHP (PHPCSExtra), and VariableAnalysis rules.
    JS/CSS scanning is disabled to avoid PHP_CodeSniffer 4.0 deprecation warnings.
  </description>

  <!-- Scan all PHP source files -->
  <file>starmus-audio-recorder.php</file>
  <file>uninstall.php</file>
  <file>src/</file>

  <!-- Exclude paths that should not be scanned -->
  <exclude-pattern>vendor/*</exclude-pattern>
  <exclude-pattern>node_modules/*</exclude-pattern>
  <exclude-pattern>tests/*</exclude-pattern>
  <exclude-pattern>*.min.js</exclude-pattern>
  <exclude-pattern>wp-assets/*</exclude-pattern>
  <exclude-pattern>build/*</exclude-pattern>

  <!-- configs -->
  <config name="testVersion" value="8.2-8.4"/>
  <config name="tabWidth" value="4"/>
  <config name="default_standard" value="."/>


  <!-- PHPCS runtime options -->
  <arg value="sp"/> <!-- Show sniff codes + progress -->
  <arg name="basepath" value="./"/>
  <arg name="colors"/>
  <arg name="extensions" value="php"/>
  <arg name="parallel" value="8"/>
  <arg name="ignore-annotations"/>
    <arg name="encoding" value="utf-8"/>
    <arg name="warning-severity" value="0"/>
    <arg name="cache" value="true"/>
    <arg name="cache-file" value=".phpcs.cache"/>
    <arg name="report" value="full"/>
    <arg name="report-file" value="phpcs-report.txt"/>
    <arg name="standard" value="."/>

  <!-- PHP Compatibility -->
  <rule ref="PHPCompatibilityWP"/>

  <!-- Core WordPress rules -->
  <config name="minimum_supported_wp_version" value="6.8"/>
  <rule ref="WordPress-Core"/>
  <rule ref="WordPress-Extra"/>
  <rule ref="WordPress-Docs"/>
  <rule ref="WordPressVIPMinimum"/>
    <rule ref="WordPress.Security"/>
    <rule ref="WordPress.DB"/>
    <rule ref="WordPress.XSS"/>

  <!-- Modern PHP / PHPCSExtra rules -->
  <rule ref="Modernize"/>
  <rule ref="Universal"/>
    <rule ref="PHPCSExtra.CodeAnalysis.EmptyStatement"/>
    <rule ref="PHPCSExtra.CodeAnalysis.UselessOverridingMethod"/>
    <rule ref="PHPCSExtra.CodeAnalysis.AssignmentInCondition"/>
    <rule ref="PHPCSExtra.CodeAnalysis.StaticThis"/>
    <rule ref="PHPCSExtra.CodeAnalysis.ShortTernary"/>

    <!-- Unused code analysis -->
    <rule ref="PHPCSExtra.CodeAnalysis.UnusedFunctionParameter"/>
    <rule ref="PHPCSExtra.CodeAnalysis.UnusedPrivateMethod"/>
    <rule ref="PHPCSExtra.CodeAnalysis.UnusedVariable"/>

  <!-- Variable Analysis -->
  <rule ref="VariableAnalysis.CodeAnalysis.VariableAnalysis"/>

  <!-- Naming conventions -->
  <rule ref="WordPress.NamingConventions.ValidFunctionName"/>
  <rule ref="WordPress.NamingConventions.PrefixAllGlobals">
    <properties>
      <property name="prefixes" type="array">
        <element value="sparxstar"/>
        <element value="starmus"/>
        <element value="aiwa"/>
        <element value="aiwacs"/>
        <element value="starisian"/>
      </property>
    </properties>
  </rule>

  <!-- i18n checks -->

  <rule ref="WordPress.WP.I18n">
    <properties>
      <property name="text_domain" type="array">
        <element value="starmus-audio-recorder"/>
      </property>
    </properties>
  </rule>

  <!-- Relax spacing rules slightly -->
  <rule ref="WordPress.WhiteSpace.OperatorSpacing.NoSpaceBefore">
     <severity>0</severity>
  </rule>
  <rule ref="WordPress.WhiteSpace.OperatorSpacing.NoSpaceAfter">
     <severity>0</severity>
  </rule>

  <!-- Optional: Disable JS/CSS sniff listeners entirely -->
  <exclude name="WordPressVIPMinimum.JS.*"/>

  <!-- Force spaces over tabs -->
  <rule ref="Generic.WhiteSpace.ScopeIndent">
    <properties>
      <property name="indent" value="4"/>
      <property name="tabIndent" value="false"/>
    </properties>
  </rule>
  <rule ref="Generic.WhiteSpace.DisallowTabIndent"/>

</ruleset>
